{
    "version": "https://jsonfeed.org/version/1",
    "title": "sina news",
    "home_page_url": "https://abuqi.github.io/sina-news",
    "feed_url": "https://abuqi.github.io/sina-news/rss.json",
    "description": "sina news zhibo",
    "items": [
        {
            "id": 3215031,
            "content_html": "",
            "url": "https://finance.sina.cn/7x24/2023-08-21/detail-imzhxxee5604495.d.html",
            "title": "【阿里巴巴旗下大湾区基金募资20亿港元】Gobi Partners近日宣布为阿里巴巴支持的基金完成了等值20亿港元（2.559亿美元）的募集目标，该基金致力于在中国南部的大湾区进行投资。戈壁大湾区管理合伙人唐啟波表示，新基金名为AEF大湾区基金（GBA），将一直开放到今年年底，接受更多有限合伙人（LP）的支持。AEF GBA基金将电子商务巨头阿里巴巴集团旗下的非营利性基金会阿里巴巴香港创业者基金（AEF）作为主要投资者，投资于粤港澳大湾区，覆盖中国香港特别行政区、澳门特别行政区以及中国广东省南部的九个城市。（投资界）",
            "date_modified": "2023-08-21T06:20:36.000Z"
        },
        {
            "id": 3215030,
            "content_html": "",
            "url": "https://finance.sina.cn/7x24/2023-08-21/detail-imzhxxec2566502.d.html",
            "title": "【北向资金净卖出超30亿元】以买卖成交额口径（挂单已成交）统计，截至目前北向资金净卖出超31亿元，其中沪股通净卖出32.68亿元，深股通净买入1.45亿元。以余额规模口径（已挂单）统计，北向资金净流出超25亿元，其中沪股通净流出29.35亿元，深股通净流入3.98亿元。",
            "date_modified": "2023-08-21T06:19:49.000Z"
        },
        {
            "id": 3215029,
            "content_html": "",
            "url": "https://finance.sina.cn/7x24/2023-08-21/detail-imzhxxcx3817919.d.html",
            "title": "  【钱江摩托1亿成立智能制造公司】天眼查App显示，近日，安徽钱江智能制造有限公司成立，法定代表人为吴萍辉，注册资本1亿人民币，经营范围含摩托车零配件制造、批发、零售、助动车制造等。股东信息显示，该公司由钱江摩托(000913)全资持股，后者大股东为吉利迈捷投资有限公司。",
            "date_modified": "2023-08-21T06:18:39.000Z"
        },
        {
            "id": 3215028,
            "content_html": "",
            "url": "https://finance.sina.cn/7x24/2023-08-21/detail-imzhxxec2566166.d.html",
            "title": "【台媒：传有人在台东外海发现疑似“雄风-2E”导弹残骸，台军紧急回应】据台湾“中时新闻网”20日报道，台军方15日至17日于屏东九鹏地区进行导弹射击操演，随后有民众在台东金樽海域发现海面上漂浮着疑似“雄风-2E”导弹第二级推进器的橘红色物体，台军方20日下午紧急回应称，不明飞行器为空对空导弹打靶测试所用靶机，已将其打捞回收。（环球网）",
            "date_modified": "2023-08-21T06:18:15.000Z"
        },
        {
            "id": 3215027,
            "content_html": "",
            "title": "据南部半岛棕榈油压榨商协会（SPPOMA）数据：2023年8月1-20日马来西亚棕榈油单产增加5.05%，出油率增长0.34%，产量增加7%。",
            "date_modified": "2023-08-21T06:16:11.000Z"
        },
        {
            "id": 3215026,
            "content_html": "",
            "url": "https://finance.sina.cn/7x24/2023-08-21/detail-imzhxxcz5788469.d.html",
            "title": "【为高管报销子女学费未按规定代扣代缴个税，博士伦北京公司被罚18.87万】信用中国网站显示，8月11日，北京博士伦眼睛护理产品有限公司因税务违法，被国家税务总局北京市税务局第一稽查局罚款约18.87万元。处罚事由显示，该单位为高管报销子女学费，未按规定代扣代缴个人所得税，2019年应补扣补缴个人所得税12.79万余元，2020年应补扣补缴个人所得税11.62万余元，2021年应补扣补缴个人所得税13.31万元，合计应补扣补缴个人所得税37.74万余元。2023年5月，该单位自行到税务机关补扣补缴上述个人所得税。",
            "date_modified": "2023-08-21T06:15:15.000Z"
        },
        {
            "id": 3215025,
            "content_html": "",
            "url": "https://finance.sina.cn/7x24/2023-08-21/detail-imzhxxcz5788275.d.html",
            "title": "【中国长城：公司可为卫星互联网建设筑牢信息安全底座】中国长城在互动平台表示，公司可为卫星互联网建设筑牢信息安全底座。",
            "date_modified": "2023-08-21T06:14:16.000Z"
        },
        {
            "id": 3215024,
            "content_html": "",
            "url": "https://finance.sina.cn/7x24/2023-08-21/detail-imzhxxec2565392.d.html",
            "title": "【俄航天集团：“进步MS-22”货运飞船已坠落太平洋】据俄罗斯卫星通讯社，俄罗斯联邦航天集团8月21日发布消息，“进步MS-22”货运飞船于早上脱离国际空间站，在太平洋非航行区域坠落。",
            "date_modified": "2023-08-21T06:14:16.000Z"
        },
        {
            "id": 3215023,
            "content_html": "",
            "url": "https://finance.sina.cn/7x24/2023-08-21/detail-imzhxxcz5787613.d.html",
            "title": "【燃气股大幅异动，美能能源深水直线拉升涨停】8月21日下午，燃气股大幅异动，美能能源深水直线拉升涨停，首华燃气、水发燃气、贵州燃气短线飙升。",
            "date_modified": "2023-08-21T06:12:06.000Z"
        },
        {
            "id": 3215022,
            "content_html": "",
            "url": "https://finance.sina.cn/7x24/2023-08-21/detail-imzhxxec2564692.d.html",
            "title": "【重庆永川全域开放1385公里自动驾驶开放测试和示范应用道路】重庆永川区人民政府副区长徐秀霞介绍，加速永川自动驾驶示范营运中心建设，增强场景应用优势。为进一步丰富自动驾驶汽车场景应用，促进形成自动驾驶产业商业模式，永川已经全域开放了1385公里的道路作为自动驾驶开放测试和示范应用道路，今年将利用永川高铁东站旁边的30亩土地来规划建设自动驾驶示范营运中心，目前项目已经进入了设计阶段，预计在明年可以建成投用。",
            "date_modified": "2023-08-21T06:11:57.000Z"
        },
        {
            "id": 3215021,
            "content_html": "",
            "title": "【美国家气象局：受飓风“费尔南达”余波影响，夏威夷或将强降雨】 据美国有线电视新闻网当地时间20日报道，美国国家气象局檀香山办公室称，飓风“费尔南达”的余波预计将在未来几天对夏威夷群岛产生影响。预计夏威夷群岛北部和东部地区将出现局部强降雨，毛伊岛、欧胡岛和考爱岛东部地区预计将有阵雨。21日可能会出现局部大雨，导致夏威夷岛出现局部洪水。毛伊岛的降雨可能主要集中在毛伊岛东部，而受致命山火影响的毛伊岛西部地区预计将继续保持干燥，21日下午到晚上可能会出现几场小阵雨。拉海纳21日、22日可能会出现零星阵雨。（央视新闻）",
            "date_modified": "2023-08-21T06:11:44.000Z"
        },
        {
            "id": 3215020,
            "content_html": "",
            "url": "https://finance.sina.cn/7x24/2023-08-21/detail-imzhxxee5602496.d.html",
            "title": "【马来西亚8月1日至20日棕榈油出口量环比增长17.4% 】据马来西亚独立检验机构AmSpec：马来西亚8月1日至20日棕榈油出口量达806,655吨，环比增长17.4%。",
            "date_modified": "2023-08-21T06:11:24.000Z"
        },
        {
            "id": 3215019,
            "content_html": "",
            "url": "https://finance.sina.cn/7x24/2023-08-21/detail-imzhxswc5918027.d.html",
            "title": "【鸿博股份主力资金净流入超5亿元居首】8月21日下午，Wind数据显示，11股主力资金净流入超1亿元，鸿博股份净流入超5亿元居首，N协昌科技净流入超4亿元，英飞特、久其软件净流入超2亿元，南天信息、华是科技、汇金股份、江苏银行、东方园林、天禾股份净流入额居前。",
            "date_modified": "2023-08-21T06:10:52.000Z"
        },
        {
            "id": 3215018,
            "content_html": "",
            "title": "【网易登记恰似chats软件著作权】天眼查App显示，近日，网易（杭州）网络有限公司“网易数帆人工智能算法软件”“恰似chats手机端应用软件”获得登记批准，版本号均为V1.0。该公司成立于2006年6月，法定代表人为丁磊，注册资本1.376亿美元，由香港网易互动娱乐有限公司全资持股。",
            "date_modified": "2023-08-21T06:10:32.000Z"
        },
        {
            "id": 3215017,
            "content_html": "",
            "url": "https://finance.sina.cn/7x24/2023-08-21/detail-imzhxswf2694956.d.html",
            "title": "【机构：三星电子上半年全球电视市占率31.2%居首】市场调研机构奥姆迪亚（Omdia）8月21日发布的一份统计数据显示，以销售额为准，三星电子今年上半年全球电视市占率为31.2%，居于首位。",
            "date_modified": "2023-08-21T06:10:07.000Z"
        },
        {
            "id": 3215016,
            "content_html": "",
            "url": "https://finance.sina.cn/7x24/2023-08-21/detail-imzhxswf2694768.d.html",
            "title": "【燃气板块异动拉升 水发燃气涨超7%】 燃气板块异动拉升，水发燃气涨超7%，蓝天燃气、美能能源、新疆火炬、东方环宇等跟涨。",
            "date_modified": "2023-08-21T06:08:56.000Z"
        },
        {
            "id": 3215015,
            "content_html": "",
            "url": "https://finance.sina.cn/7x24/2023-08-21/detail-imzhxswc5917590.d.html",
            "title": "【俄罗斯莫斯科多莫杰多沃机场和伏努科沃机场恢复正常运行】当地时间8月21日，俄罗斯莫斯科多莫杰多沃和伏努科沃两个机场发布消息称，从莫斯科时间当日8时30分（北京时间13时30分）起机场恢复正常运行，航班正常起降。（央视新闻）",
            "date_modified": "2023-08-21T06:08:35.000Z"
        },
        {
            "id": 3215014,
            "content_html": "",
            "url": "https://finance.sina.cn/7x24/2023-08-21/detail-imzhxswf2694704.d.html",
            "title": "【北大荒：近期暴雨暂未对公司生产经营造成较大影响】北大荒在互动平台表示，公司种植区域不是主要降雨地带，近期暴雨暂未对公司生产经营造成较大影响。",
            "date_modified": "2023-08-21T06:08:32.000Z"
        },
        {
            "id": 3215013,
            "content_html": "",
            "url": "https://finance.sina.cn/7x24/2023-08-21/detail-imzhxswc5917330.d.html",
            "title": "【兴发集团、上海新阳等于武汉共设私募公司，注册资本超20亿】企查查APP显示，近日，长存产业投资基金（武汉）合伙企业（有限合伙）成立，注册资本20.43亿元人民币，经营范围包含：私募股权投资基金管理、创业投资基金管理服务。企查查股权穿透显示，该公司由兴发集团、上海新阳、安集科技等共同持股。",
            "date_modified": "2023-08-21T06:07:20.000Z"
        },
        {
            "id": 3215012,
            "content_html": "",
            "url": "https://finance.sina.cn/7x24/2023-08-21/detail-imzhxswf2694320.d.html",
            "title": "【南非总统拉马福萨称支持金砖国家扩容，目前已有超20个国家正式申请加入】 彭博8月21日消息，金砖国家峰会将于本周在约翰内斯堡举行，南非总统拉马福萨对这一新兴市场组织扩容表示支持，并表示已有20多个国家正式申请加入。“金砖国家扩员将更加多元化，各国怀有共同愿望，希望世界秩序更加平衡，”拉马福萨周日在电视讲话中表示。（界面新闻）",
            "date_modified": "2023-08-21T06:06:58.000Z"
        },
        {
            "id": 3215011,
            "content_html": "",
            "url": "https://finance.sina.cn/7x24/2023-08-21/detail-imzhxswc5917174.d.html",
            "title": "【科华数据：公司与宁夏联通签署战略合作协议】科华数据(002335)在互动平台表示，公司与中国联通宁夏分公司签署“东数西算”生态合作伙伴战略合作协议，助力宁夏数字基础设施建设。",
            "date_modified": "2023-08-21T06:06:51.000Z"
        },
        {
            "id": 3215010,
            "content_html": "",
            "url": "https://finance.sina.cn/7x24/2023-08-21/detail-imzhxswc5916882.d.html",
            "title": "【机构评德国7月PPI月率：下降是由能源驱动的】该数据今天录得远低于市场预期，大部分下降仍然是由能源驱动的，与6月相比，能源价格下降了2.5%。好消息是如果你将其剔除掉，生产者价格在当月也仍然下降了0.4%。这应该最终会传导到消费者通胀上。不管怎样，对于德国经济来说，他们希望能源价格下降的影响能早日传导到消费者端。",
            "date_modified": "2023-08-21T06:05:57.000Z"
        },
        {
            "id": 3215009,
            "content_html": "",
            "url": "https://finance.sina.cn/7x24/2023-08-21/detail-imzhxswf2693707.d.html",
            "title": "【光大证券：继续全面看好金属新材料板块】光大证券：继续全面看好金属新材料板块。锂精矿价格处于高位仍利好锂资源自给率高的企业。建议关注天齐锂业、赣锋锂业、中矿资源；青海建设世界级盐湖产业基地被再度提及，国内自主可控的盐湖资源具有重大战略意义，建议关注盐湖股份、藏格矿业。作为未来锂价调节的平衡器，钠电池产业化积极推进中，优先关注从零到一的钠电负极硬碳环节，建议关注元力股份。",
            "date_modified": "2023-08-21T06:04:52.000Z"
        },
        {
            "id": 3215007,
            "content_html": "",
            "url": "https://finance.sina.cn/7x24/2023-08-21/detail-imzhxswc5916401.d.html",
            "title": "欧洲基准天然气价格上涨18%。",
            "date_modified": "2023-08-21T06:04:16.000Z"
        },
        {
            "id": 3215006,
            "content_html": "",
            "url": "https://finance.sina.cn/7x24/2023-08-21/detail-imzhxswc5916399.d.html",
            "title": "【安井食品：安井冻品先生重点打造酸菜鱼等，安井小厨聚焦小酥肉和荷香糯米鸡】安井食品8月21日在互动平台称，在预制菜板块，安井冻品先生重点打造酸菜鱼和烤鱼，安井小厨聚焦小酥肉和荷香糯米鸡，持续进行大单品培育；同时公司将安井、安井小厨品牌分别授权新宏业、新柳伍使用，复用安井现有经销商渠道推动小龙虾业务尤其是调味小龙虾产品实现业务增量。",
            "date_modified": "2023-08-21T06:04:16.000Z"
        },
        {
            "id": 3215004,
            "content_html": "",
            "url": "https://finance.sina.cn/7x24/2023-08-21/detail-imzhxswc5916262.d.html",
            "title": "【港股科网股走弱 中国有赞跌超3%】港股科网股走弱。截至发稿，香港科技探索(01137.HK)跌超4%，中国有赞(08083.HK)跌超4%，赤子城科技(09911.HK)跌超3%。",
            "date_modified": "2023-08-21T06:03:49.000Z"
        },
        {
            "id": 3215003,
            "content_html": "",
            "title": "【水发燃气：LNG设计产能为日处理110万方天然气，目前设备运行稳定，基本按产能上限运行】公司提氦气产量和每日加工LNG量息息相关。公司全资子公司鄂尔多斯市水发燃气有限公司主业是加工LNG，副产品为氦气和重烃。LNG设计产能为日处理110万方天然气，对应的提氦设备设计产能约为600方/日，截至目前设备运行稳定，除大修等特殊情况，基本是按产能上限运行。",
            "date_modified": "2023-08-21T06:03:42.000Z"
        },
        {
            "id": 3215002,
            "content_html": "",
            "url": "https://finance.sina.cn/7x24/2023-08-21/detail-imzhxswf2693196.d.html",
            "title": "【上海钢联设科技服务子公司，含AI软件开发业务】企查查APP显示，近日，上海钢联科技服务有限公司成立，注册资本5000万元人民币，经营范围包含：人工智能应用软件开发；人工智能基础软件开发；金属矿石销售；有色金属合金销售等。企查查股权穿透显示，该公司由上海钢联(300226)100%控股。",
            "date_modified": "2023-08-21T06:02:58.000Z"
        },
        {
            "id": 3215001,
            "content_html": "",
            "url": "https://finance.sina.cn/7x24/2023-08-21/detail-imzhxswc5916021.d.html",
            "title": "【日媒：岸田文雄9月将与伊朗总统莱希会谈，议题或涉及核开发、资产解冻等】 共同社8月21日消息，伊朗外交消息人士透露，日伊两国政府已达成一致，日本首相岸田文雄和伊朗总统莱希将在9月召开联合国大会的美国纽约举行会谈。岸田和莱希去年9月在纽约出席联大之际也曾举行会谈。据报道，预计两国首脑将就伊朗的核开发、向俄罗斯提供无人机问题展开讨论。鉴于运往日本的原油大多要经过霍尔木兹海峡，预计日方将会强调确保航行安全的重要性。伊朗外交人士称，莱希将在会谈中邀请岸田访问伊朗。莱希还将要求日方对根据美国的制裁在日本冻结的伊朗资产进行解冻，该笔资产估计有30亿美元左右。(界面新闻）",
            "date_modified": "2023-08-21T06:02:45.000Z"
        },
        {
            "id": 3215000,
            "content_html": "",
            "url": "https://finance.sina.cn/7x24/2023-08-21/detail-imzhxswh5731241.d.html",
            "title": "【规范管理网约车聚合平台 中消协开展社会监督】中国消费者协会围绕交通运输部等五部门关于规范管理网约车聚合平台有关通知开展社会监督。中消协表示，针对网约车聚合平台服务，交通运输部办公厅、工业和信息化部办公厅、公安部办公厅、国家市场监督管理总局办公厅、国家互联网信息办公室秘书局联合发布《关于切实做好网约车聚合平台规范管理有关工作的通知》（以下简称《通知》）。《通知》从“提高思想认识，高度重视网约车聚合平台规范管理工作”“压实企业责任，保障乘客和驾驶员合法权益”“规范经营行为，维护公平竞争市场秩序”“加强协同配合，提升监管能力和水平”“强化底线思维，切实维护行业安全稳定”五个方面对网约车聚合平台消费者权益保护的责任作出了明确规定。",
            "date_modified": "2023-08-21T06:02:08.000Z"
        },
        {
            "id": 3214999,
            "content_html": "",
            "url": "https://finance.sina.cn/7x24/2023-08-21/detail-imzhxswf2692943.d.html",
            "title": "【银河证券：政策释放积极信号，看好家居消费信心提振】银河证券：政策支持带动竣工快速修复，未来将对家居需求形成支撑，2023年1~7月，全国房屋累计竣工面积达到3.84亿平方米，同比增长20.5%，7月单月为0.45亿平方米，同比增长33.14%。疫后线下消费场景修复，需求复苏带动前端销售回暖，家居龙头信心十足，积极推动营销策划，全年有望实现稳增，近期关注金九银十销售表现。建议关注：定制龙头欧派家居、索菲亚、志邦家居及金牌厨柜；软体龙头顾家家居、慕思股份。",
            "date_modified": "2023-08-21T06:02:03.000Z"
        },
        {
            "id": 3214998,
            "content_html": "",
            "url": "https://finance.sina.cn/7x24/2023-08-21/detail-imzhxswc5915621.d.html",
            "title": "日经225指数收盘涨0.37%，报31565.64点。东证指数收涨0.2%，报2241.49点。",
            "date_modified": "2023-08-21T06:01:16.000Z"
        },
        {
            "id": 3214997,
            "content_html": "",
            "url": "https://finance.sina.cn/7x24/2023-08-21/detail-imzhxsvz3944951.d.html",
            "title": "【收购太平洋咖啡？柠季：不予置评】8月21日，有消息称华润有意出售旗下咖啡连锁品牌太平洋咖啡，买方为手打柠檬茶品牌柠季，预计该笔交易金额为3亿元—5亿元。针对此消息，柠季方面相关负责人对记者表示，不予置评。有知情人士向记者透露，目前太平洋咖啡确实在寻求引入战略投资人，或出售较大部分股份或全部出售股份。（新京报）",
            "date_modified": "2023-08-21T06:01:13.000Z"
        },
        {
            "id": 3214996,
            "content_html": "",
            "url": "https://finance.sina.cn/7x24/2023-08-21/detail-imzhxswf2692413.d.html",
            "title": "德国7月PPI年率 -6%，预期-5.10%，前值0.10%。",
            "date_modified": "2023-08-21T06:00:22.000Z"
        },
        {
            "id": 3214995,
            "content_html": "",
            "url": "https://finance.sina.cn/7x24/2023-08-21/detail-imzhxswf2692362.d.html",
            "title": "德国7月PPI月率 -1.1%，预期-0.20%，前值-0.30%。",
            "date_modified": "2023-08-21T06:00:15.000Z"
        },
        {
            "id": 3214993,
            "content_html": "",
            "url": "https://finance.sina.cn/7x24/2023-08-21/detail-imzhxswc5915009.d.html",
            "title": "【美银证券：下调京东目标价至200港元 评级买入】美银证券发表报告指，京东第二季度营收2879亿元，同比增长8%。报告引述集团指7月核心GMV增速超过行业增速，但由于基数较高和需求疲弱，较第二季的双位数增速有所放缓；另2023财年京东零售的营运利润率目标为按年持平。该行将集团2023及24年经调整净利润预测下调1%至2%，以反映公司稳步投资核心电子商务能力和持续增长的战略，将H股目标价由220港元下调至200港元，并因前景加快和潜在刺激因素，维持买入评级。",
            "date_modified": "2023-08-21T05:59:20.000Z"
        },
        {
            "id": 3214992,
            "content_html": "",
            "title": "【君正集团：绿色低碳环保可降解塑料循环产业链各项目将在2023年年底和2024年年初陆续投产】君正集团8月21日在互动平台表示，公司绿色低碳环保可降解塑料循环产业链项目目前处于建设阶段，该产业链对应的各项目将在2023年年底和2024年年初陆续投产。",
            "date_modified": "2023-08-21T05:58:55.000Z"
        },
        {
            "id": 3214991,
            "content_html": "",
            "url": "https://finance.sina.cn/7x24/2023-08-21/detail-imzhxswf2692028.d.html",
            "title": "【江苏、海南、贵州已成立省级掼蛋运动协会】 据微信公众号“贵州省掼蛋运动协会”消息称，8月18日下午，贵州省掼蛋运动协会成立仪式在贵阳举行。本次成立大会是在贵州省体育总会指导下，由贵商总会支持、贵州省掼蛋运动协会主办的。会上，宣读了贵州省民政厅准予该协会成立登记的批复，相关领导为协会揭牌，贵商总会为贵州省掼蛋运动协会颁发团体会员会牌。此外，查询全国社会组织信用信息公示平台发现，在贵州之前，全国已有江苏、海南两省已成立了省级掼蛋运动协会。",
            "date_modified": "2023-08-21T05:58:51.000Z"
        },
        {
            "id": 3214990,
            "content_html": "",
            "url": "https://finance.sina.cn/7x24/2023-08-21/detail-imzhxswf2691966.d.html",
            "title": "【农业农村部发通知要求建立牛蛙养殖尾水治理模式】据农业农村部官网消息，为推进牛蛙养殖产业持续健康发展，保障牛蛙养殖主体合法权益，农业农村部办公厅近日印发《关于推进牛蛙养殖产业持续健康发展的通知》，提出要建立牛蛙养殖尾水治理技术模式，对“一刀切”禁养牛蛙的不合理政策予以纠正，因地制宜、积极发展“牛蛙经济”等。",
            "date_modified": "2023-08-21T05:58:32.000Z"
        },
        {
            "id": 3214989,
            "content_html": "",
            "url": "https://finance.sina.cn/7x24/2023-08-21/detail-imzhxswf2691798.d.html",
            "title": "【港股电影概念股走强 橙天嘉禾涨超9%】港股电影概念股走强，截至发稿，澄天嘉禾涨超9%，猫眼娱乐涨超6%。",
            "date_modified": "2023-08-21T05:57:43.000Z"
        },
        {
            "id": 3214988,
            "content_html": "",
            "url": "https://finance.sina.cn/7x24/2023-08-21/detail-imzhxswf2691782.d.html",
            "title": "【俄罗斯莫斯科多莫杰多沃机场临时限制航班起降】当地时间8月21日，俄罗斯莫斯科多莫杰多沃机场发布消息称，出于安全考虑，从莫斯科时间当天06时26分（北京时间11时26分）起，临时限制机场航班的起降。（央视新闻）",
            "date_modified": "2023-08-21T05:57:40.000Z"
        },
        {
            "id": 3214987,
            "content_html": "",
            "url": "https://finance.sina.cn/7x24/2023-08-21/detail-imzhxswc5914524.d.html",
            "title": "【海河“23·7”流域性特大洪水中 84座大中型水库拦洪28.5亿立方米】8月21日，水利部召开海河“23·7”流域性特大洪水防御情况新闻发布会，会上水利部副部长刘伟平表示，此次海河流域性特大洪水防御过程中，运用84座大中型水库拦洪28.5亿立方米，调度北关、卢沟桥等关键枢纽有序分泄洪水，启用8处蓄滞洪区分洪蓄洪滞洪，最大蓄洪25.3亿立方米，充分发挥流域防洪工程体系防洪减灾综合作用，最大限度减少洪水影响和损失。（中青报）",
            "date_modified": "2023-08-21T05:56:53.000Z"
        },
        {
            "id": 3214986,
            "content_html": "",
            "url": "https://finance.sina.cn/7x24/2023-08-21/detail-imzhxswc5914392.d.html",
            "title": "【环保股午后开启二波攻势，超越科技20CM 涨停】环保股午后开启二波攻势，超越科技20CM涨停，清研环境涨超15%，联合水务、钱江生化相继封板，远达环保短线飙升。",
            "date_modified": "2023-08-21T05:56:16.000Z"
        },
        {
            "id": 3214985,
            "content_html": "",
            "url": "https://finance.sina.cn/7x24/2023-08-21/detail-imzhxswc5914296.d.html",
            "title": "小米集团(01810.HK)跌超3%，成交额超4亿港元。",
            "date_modified": "2023-08-21T05:55:49.000Z"
        },
        {
            "id": 3214984,
            "content_html": "",
            "url": "https://finance.sina.cn/7x24/2023-08-21/detail-imzhxswc5914197.d.html",
            "title": "【建工修复：在一带一路国家尚没有开展相关业务】 建工修复在互动平台表示，公司支持国家“一带一路”政策，但目前在一带一路国家尚没有开展相关业务。",
            "date_modified": "2023-08-21T05:55:16.000Z"
        },
        {
            "id": 3214983,
            "content_html": "",
            "url": "https://finance.sina.cn/7x24/2023-08-21/detail-imzhxswf2691296.d.html",
            "title": "【农业板块下挫 万辰生物跌超8%】万辰生物、华绿生物双双跌超8%，众兴菌业、万向德农、雪榕生物等跌幅靠前。",
            "date_modified": "2023-08-21T05:55:10.000Z"
        },
        {
            "id": 3214982,
            "content_html": "",
            "url": "https://finance.sina.cn/7x24/2023-08-21/detail-imzhxswf2691116.d.html",
            "title": "【熊去氧胆酸板块持续走低，宣泰医药跌超4%】熊去氧胆酸板块持续走低，宣泰医药跌超4%，广生堂跌超3%，吉贝尔跌超2%，赛托生物、海辰药业、共同药业、川宁生物跟跌。",
            "date_modified": "2023-08-21T05:54:04.000Z"
        },
        {
            "id": 3214981,
            "content_html": "",
            "url": "https://finance.sina.cn/7x24/2023-08-21/detail-imzhxswh5729568.d.html",
            "title": "星帅尔：公司上半年光伏组件出货量约0.8GW，预计全年可达1.5-1.7GW。",
            "date_modified": "2023-08-21T05:53:24.000Z"
        },
        {
            "id": 3214980,
            "content_html": "",
            "url": "https://finance.sina.cn/7x24/2023-08-21/detail-imzhxswc5913789.d.html",
            "title": "【星帅尔：公司上半年光伏组件出货量约0.8GW，预计全年可达1.5GW-1.7GW】星帅尔近期在接受调研时表示，公司上半年光伏组件出货量约0.8GW，预计全年可达1.5-1.7GW。公司光伏组件与储能系统配套销售，已开始小批量供货。争取在Q3与客户有批量交付。",
            "date_modified": "2023-08-21T05:52:49.000Z"
        }
    ]
}