{
    "version": "https://jsonfeed.org/version/1",
    "title": "sina news",
    "home_page_url": "https://abuqi.github.io/sina-news",
    "feed_url": "https://abuqi.github.io/sina-news/rss.json",
    "description": "sina news zhibo",
    "items": [
        {
            "id": 3160213,
            "content_html": "",
            "url": "https://finance.sina.cn/7x24/2023-06-30/detail-imyzafim1025787.d.html",
            "title": "【中国人民银行行长易纲会见联合国常务副秘书长阿明娜·穆罕默德】据央行，2023年6月30日，中国人民银行行长易纲会见来访的联合国常务副秘书长阿明娜·穆罕默德一行。双方就可持续发展、发展融资、气候变化等问题交换了意见。",
            "date_modified": "2023-06-30T09:17:01.000Z"
        },
        {
            "id": 3160212,
            "content_html": "",
            "url": "https://finance.sina.cn/7x24/2023-06-30/detail-imyzafin7802872.d.html",
            "title": "【欧元区核心通胀再次加速 欧央行势必加息到底】数据显示，欧元区核心通货膨胀在6月份再次加速，这对欧洲央行来说是一个挫折，可能会加强其下个月提高利率的决心，这种恶化可能会使总体通胀指标的改善黯然失。预计美联储青睐的PCE数据今晚可能继续保持在高位，这些该数据表明，全球央行官员仍在艰难前行。数据公布后，市场对欧洲央行峰值利率的押注几乎没有变化，仍为4%。",
            "date_modified": "2023-06-30T09:16:49.000Z"
        },
        {
            "id": 3160211,
            "content_html": "",
            "url": "https://finance.sina.cn/7x24/2023-06-30/detail-imyzafin7802700.d.html",
            "title": "【西门子、空客等欧企反对拟议中的欧盟人工智能监管规定，称有可能损害竞争力】包括西门子和空客在内的数十家欧洲最大企业公开反对拟议中的欧盟人工智能监管规定，称这些规定有可能损害竞争力，但却无法应对潜在的挑战。在一封由150多名高管签署的公开信中，这些公司告诉欧洲的机构，人工智能提供了“重新进入技术前沿的机会”，但过于严厉的监管可能会扼杀这一机会。",
            "date_modified": "2023-06-30T09:16:27.000Z"
        },
        {
            "id": 3160210,
            "content_html": "",
            "url": "https://finance.sina.cn/7x24/2023-06-30/detail-imyzafim1025040.d.html",
            "title": "【105家券商文化建设评级结果出炉 国君、南京、兴业、银河、中信5家获AA级】中证协发布2022年度券商文化建设评估结果，参与本次评估共105家证券公司，A类AA级公司5家，A类A级公司7家，B类BB级公司10家，B类B级公司24家。国泰君安、南京证券、兴业证券、银河证券、中信证券获AA级券商，安信证券、东北证券、国信证券、国元证券、申万宏源、中泰证券、中信建投、获A类券商。财信证券、东方证券、东海证券、国海证券、国联证券、华泰证券、山西证券、长江证券、招商证券、浙商证券获BB级。",
            "date_modified": "2023-06-30T09:15:20.000Z"
        },
        {
            "id": 3160209,
            "content_html": "",
            "title": "【昆工科技：修订并签署年产2000万kVAh新型铅炭长时储能电池生产基地项目投资协议书】昆工科技6月30日公告，公司于2月6日召开第四届董事会第二次会议审议通过《关于拟投资建设年产2000万kVAh新型铅炭长时储能电池生产基地项目暨签署<投资协议书>的议案》。经双方协商一致，公司与银川高新技术产业开发区管委会针对协议条款内容进行了修订，并于近日签署了协议。项目计划总投资24亿元，其中一期计划投资12亿元，二期计划投资12亿元。项目全部建成达产后，预估年产值160亿元（其中一期全部达产后年产值不低于80亿元）。",
            "date_modified": "2023-06-30T09:14:54.000Z"
        },
        {
            "id": 3160208,
            "content_html": "",
            "url": "https://finance.sina.cn/7x24/2023-06-30/detail-imyzafin7801212.d.html",
            "title": "【山东海化：拟在泰安市岱岳区投资建设以岩盐资源开发为基础的盐化工及其产业链项目】山东海化公告，拟在泰安市岱岳区投资建设以岩盐资源开发为基础的盐化工及其产业链项目，并利用岩盐开采盐穴建设储能绿色低碳产业，初步规划建设300MW压缩空气储能电站项目，其中岩盐开采和精制盐场建设总投资约9亿元，盐穴储能总投资约15亿元。",
            "date_modified": "2023-06-30T09:12:53.000Z"
        },
        {
            "id": 3160207,
            "content_html": "",
            "url": "https://finance.sina.cn/7x24/2023-06-30/detail-imyzafim1023828.d.html",
            "title": "【德邦股份：与京东物流拟签订《资产转让协议》】德邦股份公告，与京东物流拟签订《资产转让协议》，约定公司及其控股子公司将以合计不超过人民币1.06亿元（不含税）的自有资金购买京东物流及其控股子公司83个转运中心的部分资产。",
            "date_modified": "2023-06-30T09:12:09.000Z"
        },
        {
            "id": 3160206,
            "content_html": "",
            "url": "https://finance.sina.cn/7x24/2023-06-30/detail-imyzafim1023754.d.html",
            "title": "【上期所：国际铜期货合约交易保证金比例调整为8%】上期所发布通知，自2023年7月4日（周二）收盘结算时起，国际铜期货合约的交易保证金比例调整为8%，涨跌停板幅度调整为6%；原油期货合约的交易保证金比例调整为10%，涨跌停板幅度调整为8%；如遇上述交易保证金比例、涨跌停板幅度与现行执行的交易保证金比例、涨跌停板幅度不同时，则按两者中比例高、幅度大的执行。",
            "date_modified": "2023-06-30T09:11:55.000Z"
        },
        {
            "id": 3160205,
            "content_html": "",
            "url": "https://finance.sina.cn/7x24/2023-06-30/detail-imyzafin7800863.d.html",
            "title": "【中国银行间交易商协会：大力推进不动产信托资产支持票据（银行间类REITs）业务】中国银行间交易商协会文件表示，重点支持租赁住房、能源、公用事业、交通运输、仓储物流、新基建、生态环保、产业园区、水利设施、旅游基础设施等领域通过发行类REITs有效盘活存量资产，满足企业轻资产运3营、提升资产运营管理效率及降低资产负债率等多样化融资需求，形成存量资产和新增投资的良性循环。",
            "date_modified": "2023-06-30T09:11:46.000Z"
        },
        {
            "id": 3160204,
            "content_html": "",
            "url": "https://finance.sina.cn/7x24/2023-06-30/detail-imyzafin7799403.d.html",
            "title": "【润都股份：阿齐沙坦获得化学原料药上市申请批准】润都股份公告，公司近日收到国家药监局核准签发的阿齐沙坦《化学原料药上市申请批准通知书》。该药品主要适应症用于高血压治疗。",
            "date_modified": "2023-06-30T09:08:19.000Z"
        },
        {
            "id": 3160203,
            "content_html": "",
            "title": "【外汇局：一季度货物贸易顺差及进出口规模均处于历史同期次高值】国家外汇管理局副局长、新闻发言人王春英表示，2023年一季度，我国国际收支基本平衡。其中，经常账户顺差815亿美元，为历史同期较高水平，与同期国内生产总值（GDP）之比为2.0%，保持在合理均衡区间。货物贸易顺差及进出口规模均处于历史同期次高值。一季度，我国国民经济持续恢复，经济运行实现良好开局，国际收支口径的货物贸易顺差1299亿美元，出口7392亿美元，进口6092亿美元，三项数据均为历史同期次高值。",
            "date_modified": "2023-06-30T09:08:00.000Z"
        },
        {
            "id": 3160202,
            "content_html": "",
            "title": "欧元区CPI数据回落，德国10年期国债收益率上涨3.40个基点，现报2.447%。德国2年期国债收益率上涨1.8个基点，现报3.273%。意大利10年期国债收益率上涨5.9个基点，现报4.150%。",
            "date_modified": "2023-06-30T09:06:38.000Z"
        },
        {
            "id": 3160201,
            "content_html": "",
            "url": "https://finance.sina.cn/7x24/2023-06-30/detail-imyzafin7798365.d.html",
            "title": "印度NIFTY指数涨1%。",
            "date_modified": "2023-06-30T09:06:30.000Z"
        },
        {
            "id": 3160200,
            "content_html": "",
            "url": "https://finance.sina.cn/7x24/2023-06-30/detail-imyzafin7798014.d.html",
            "title": "【机构评欧元区CPI数据：不要指望欧洲央行放弃鹰派立场】好消息是，尽管德国的基数效应较高，但欧元区6月CPI年率初值进一步下降。然而，核心通胀率仍然居高不下，这点在我们之前看的西班牙报告中也有明显证据。欧元可能会对总体数据做出一些反应，但考虑到核心数据的情况，请不要指望欧洲央行在鹰派立场上有任何松动。",
            "date_modified": "2023-06-30T09:05:53.000Z"
        },
        {
            "id": 3160199,
            "content_html": "",
            "url": "https://finance.sina.cn/7x24/2023-06-30/detail-imyzafiq8693678.d.html",
            "title": "【天源环保：签订2.06亿元日常经营合同】天源环保公告，与中联宏信勘察设计有限公司作为联合体，共同与武定县城市建设开发投资有限公司在武定县签订了《楚雄州武定县城污水管网改造建设项目工程总承包合同》，暂估签约合同价为2.06亿元。",
            "date_modified": "2023-06-30T09:05:02.000Z"
        },
        {
            "id": 3160198,
            "content_html": "",
            "url": "https://finance.sina.cn/7x24/2023-06-30/detail-imyzafim1020373.d.html",
            "title": "【广东证监局：加强与司法部门交流协作 统筹推进纠纷多元化解和金融风险防范化解】据广东证监局消息，近日，该局与广州市中级人民法院召开座谈会，围绕诉调对接、诉源治理等主题进行交流。会上，各方就进一步完善在线诉调对接机制、解决诉前、诉中调解有关工作进行交流。下一步，广东证监局将持续健全辖区证券执法司法体制机制，加强与司法部门交流协作，统筹推进纠纷多元化解和金融风险防范化解，切实维护投资者合法权益。",
            "date_modified": "2023-06-30T09:04:57.000Z"
        },
        {
            "id": 3160197,
            "content_html": "",
            "url": "https://finance.sina.cn/7x24/2023-06-30/detail-imyzafim1020184.d.html",
            "title": "【国新能源：收到政府补助约6605万元】国新能源公告，自6月22日至公告日，公司及下属公司收到的与收益相关的政府补助共计6605.44万元。",
            "date_modified": "2023-06-30T09:04:29.000Z"
        },
        {
            "id": 3160196,
            "content_html": "",
            "url": "https://finance.sina.cn/7x24/2023-06-30/detail-imyzafin7796741.d.html",
            "title": "【胡锡进：四只个股今天五红一绿 我对自己实现“成功进入”感到满意】胡锡进在新浪财经专栏发文表示，今天是老胡进入股市第四天，昨天到收盘时，我已经亏损900多元，占实际股票持有额的0.9%。今天我选择不操作，因为大盘翻红，我扳回了664元，占实际持有额的0.6%几，亏损收窄为282元。我虽然仍亏着，但今天回涨的幅度与A股上涨幅度持平，这让我这个新手很高兴。过去几天我把10万元资金变成股票，达到了我的预期购买速度。现在我手上已经有两只基金，四只个股，它们今天五红一绿，我对自己实现“成功进入”感到满意。",
            "date_modified": "2023-06-30T09:03:05.000Z"
        },
        {
            "id": 3160195,
            "content_html": "",
            "url": "https://finance.sina.cn/7x24/2023-06-30/detail-imyzafin7796288.d.html",
            "title": "贝壳(BEKE.N)：于6月29日耗资近500万美元回购近101万股。",
            "date_modified": "2023-06-30T09:02:10.000Z"
        },
        {
            "id": 3160194,
            "content_html": "",
            "url": "https://finance.sina.cn/7x24/2023-06-30/detail-imyzafim1018776.d.html",
            "title": "欧元区6月核心CPII月率初值 0.4%，前值0.3%；年率初值 6.8%，预期6.7%，前值6.9%。",
            "date_modified": "2023-06-30T09:00:50.000Z"
        },
        {
            "id": 3160193,
            "content_html": "",
            "url": "https://finance.sina.cn/7x24/2023-06-30/detail-imyzafin7795811.d.html",
            "title": "欧元区5月失业率 6.5%，预期6.50%，前值6.50%。",
            "date_modified": "2023-06-30T09:00:37.000Z"
        },
        {
            "id": 3160192,
            "content_html": "",
            "url": "https://finance.sina.cn/7x24/2023-06-30/detail-imyzafim1018587.d.html",
            "title": "欧元区6月CPI月率0.3%，预期0.30%，前值0.00%；年率初值5.5%，创2022年1月以来新低，预期5.60%，前值6.1%。",
            "date_modified": "2023-06-30T09:00:27.000Z"
        },
        {
            "id": 3160191,
            "content_html": "",
            "title": "中证指数：中证指数有限公司将于2023年6月30日正式发布中证智选500趋势成长指数，为市场提供多样化的投资标的。中证智选500趋势成长指数从中证500指数样本中选取50只成长性较好、动量较高的上市公司证券作为指数样本。",
            "date_modified": "2023-06-30T08:59:54.000Z"
        },
        {
            "id": 3160190,
            "content_html": "",
            "url": "https://finance.sina.cn/7x24/2023-06-30/detail-imyzafim1018299.d.html",
            "title": "【中国海洋石油：夏庆龙因工作需要辞任公司总裁】中国海洋石油6月30日在港交所公告，夏庆龙因工作需要，辞任公司执行董事及总裁，自2023年6月30日生效。自2023年6月30日起，公司执行董事、首席执行官周心怀兼任公司总裁。",
            "date_modified": "2023-06-30T08:59:30.000Z"
        },
        {
            "id": 3160189,
            "content_html": "",
            "url": "https://finance.sina.cn/7x24/2023-06-30/detail-imyzafii2576516.d.html",
            "title": "【气派科技：获得政府补助约4883.51万元】气派科技公告，公司及全资子公司广东气派科技有限公司、控股子公司气派芯竞科技有限公司今年累计获得政府补助款项约4883.51万元。",
            "date_modified": "2023-06-30T08:59:02.000Z"
        },
        {
            "id": 3160188,
            "content_html": "",
            "url": "https://finance.sina.cn/7x24/2023-06-30/detail-imyzafiq8692427.d.html",
            "title": "【天源环保：签订日常经营合同】天源环保公告，公司与中联宏信勘察设计有限公司（联合体成员）作为联合体，共同与武定县城市建设开发投资有限公司在武定县签订了《楚雄州武定县城污水管网改造建设项目工程总承包合同》），暂估签约合同价为人民币（大写）贰亿伍佰捌拾陆万伍仟捌佰捌拾陆元整（¥20,586.5886万元）。",
            "date_modified": "2023-06-30T08:58:56.000Z"
        },
        {
            "id": 3160187,
            "content_html": "",
            "url": "https://finance.sina.cn/7x24/2023-06-30/detail-imyzafin7794647.d.html",
            "title": "【杭州新增挂牌4宗地块 总起始价62.5亿元】6月30日，据杭州市规划和自然资源披露，杭州新增挂牌4宗地块，总出让面积14.88万平方米，总起始价约62.5亿元，预计挂牌报价时间为7月21日至8月1日。(新京报)",
            "date_modified": "2023-06-30T08:56:51.000Z"
        },
        {
            "id": 3160186,
            "content_html": "",
            "url": "https://finance.sina.cn/7x24/2023-06-30/detail-imyzafiq8692013.d.html",
            "title": "【中国广电全国固定语音业务网、互联网骨干网、内容集成播控平台开通上线】从6月30日在京举行的中国广电数字化赋能大会上获悉，中国广电全国固定语音业务网、互联网骨干网（CBNET）、内容集成播控平台开通上线。这是全国有线电视网络整合和广电5G建设一体化发展取得的新发展成果。(新华社)",
            "date_modified": "2023-06-30T08:56:22.000Z"
        },
        {
            "id": 3160185,
            "content_html": "",
            "url": "https://finance.sina.cn/7x24/2023-06-30/detail-imyzafii2575720.d.html",
            "title": "【爱康科技：全资子公司签署租赁协议】爱康科技公告，全资子公司苏州爱康光电科技有限公司（简称“苏州爱康光电”）拟与浙江国康新能源科技有限公司签署《租赁协议》，苏州爱康光电将位于长兴县煤山镇浙能智慧能源科技产业园创业创新大道交一环路北侧地块整体租赁给国康新能源用于光伏电池生产。租赁物包含土地（总用地面积113179平方米）及厂房（总建筑面积73829平方米附属机电设施），租赁期限为2年，年租金3819.40万元（含税）。",
            "date_modified": "2023-06-30T08:54:16.000Z"
        },
        {
            "id": 3160184,
            "content_html": "",
            "url": "https://finance.sina.cn/7x24/2023-06-30/detail-imyzafiq8691581.d.html",
            "title": "【深铁辛杰：深铁投资万科是一个正确的选择】6月30日万科股东大会上，作为大股东的代表，深铁董事长辛杰对郁亮带领的万科团队过去三年表现给予肯定。辛杰指出，在房地产行业深刻变革下，万科牢牢守住了安全底线，作为股东感到很欣慰。他表态，称万科是货真价实的万科，是有现金流支撑的万科，深铁投资万科是一个正确的选择。辛杰表示，深铁坚持长期主义，对万科的认同和支持不会因为市场一时的波动而变化，像三年前一样，深铁将坚定不移地看好万科的长期发展前景，作为股东始终不渝全方位支持万科的健康发展，继续在多个领域、多个项目以及新的赛道上与万科深入合作。",
            "date_modified": "2023-06-30T08:53:52.000Z"
        },
        {
            "id": 3160183,
            "content_html": "",
            "url": "https://finance.sina.cn/7x24/2023-06-30/detail-imyzafin7793084.d.html",
            "title": "【外汇局：一季度货物贸易顺差及进出口规模均处于历史同期次高值】国家外汇管理局副局长、新闻发言人王春英就2023年一季度国际收支和3月末国际投资头寸状况答记者问。王春英表示，2023年一季度，我国国际收支基本平衡。货物贸易顺差及进出口规模均处于历史同期次高值。一季度，我国国民经济持续恢复，经济运行实现良好开局，国际收支口径的货物贸易顺差1299亿美元，出口7392亿美元，进口6092亿美元，三项数据均为历史同期次高值。",
            "date_modified": "2023-06-30T08:52:52.000Z"
        },
        {
            "id": 3160182,
            "content_html": "",
            "url": "https://finance.sina.cn/7x24/2023-06-30/detail-imyzafim1015793.d.html",
            "title": "【印尼旅游部副部长：“巴厘岛旅游需提前一年预约”传闻不实】印尼旅游和创意经济部副部长阿玉·马蒂尼表示，有关“巴厘岛旅游需要提前一年预约”的传闻不实，巴厘岛乃至整个印尼依然欢迎全球各地游客的到来。",
            "date_modified": "2023-06-30T08:52:32.000Z"
        },
        {
            "id": 3160181,
            "content_html": "",
            "url": "https://finance.sina.cn/7x24/2023-06-30/detail-imyzafin7792385.d.html",
            "title": "【柳药集团今日涨停 三机构净买入1.82亿元】柳药集团今日涨停，成交额8.80亿元，换手率9.93%，盘后龙虎榜数据显示，沪股通专用席位买入6407.24万元并卖出8115.15万元，三机构净买入1.82亿元，二机构净卖出5017.33万元。",
            "date_modified": "2023-06-30T08:51:05.000Z"
        },
        {
            "id": 3160180,
            "content_html": "",
            "url": "https://finance.sina.cn/7x24/2023-06-30/detail-imyzafim1015193.d.html",
            "title": "【商务部：5个自贸区及海南自贸港试点对接国际高标准经贸规则】从国新办举行的国务院政策例行吹风会上了解到，国务院近日印发《关于在有条件的自由贸易试验区和自由贸易港试点对接国际高标准推进制度型开放的若干措施》 ，率先在上海、广东、天津、福建、北京等5个具备条件的自贸试验区和海南自由贸易港主动开展试点，对接国际高标准经贸规则，推进制度型开放。",
            "date_modified": "2023-06-30T08:50:59.000Z"
        },
        {
            "id": 3160179,
            "content_html": "",
            "url": "https://finance.sina.cn/7x24/2023-06-30/detail-imyzafim1014996.d.html",
            "title": "【全国首单地方增信产业资产支持证券落地四川】6月29日，在自贡市委、市政府，上交所，四川证监局的支持和指导下，自贡市公交集团有限责任公司作为原始权益人完成“华西-自贡公交经营收费收益权绿色资产支持专项计划”成功簿记，发行规模4.75亿元，产品期限5年。",
            "date_modified": "2023-06-30T08:50:40.000Z"
        },
        {
            "id": 3160178,
            "content_html": "",
            "url": "https://finance.sina.cn/7x24/2023-06-30/detail-imyzafim1014468.d.html",
            "title": "【安井食品今日跌6.43% 三机构净卖出2.8亿元】安井食品今日跌6.43%，成交额10.95亿元，换手率2.50%，盘后龙虎榜数据显示，沪股通专用席位买入1.08亿元并卖出1.53亿元，三机构净买入1.43亿元，三机构净卖出2.8亿元。",
            "date_modified": "2023-06-30T08:49:37.000Z"
        },
        {
            "id": 3160177,
            "content_html": "",
            "url": "https://finance.sina.cn/7x24/2023-06-30/detail-imyzafim1014089.d.html",
            "title": "【咸亨国际：公司无人机相关产品及服务在公司整体营收占比非常小】咸亨国际公告，公司无人机相关产品及服务在公司整体营收占比非常小。公司旗下涉及无人机业务的有航空研究院和航空自动化，主要负责给能源领域的相关用户提供无人机巡检服务。2022年，航空研究院和航空自动化的营业收入分别为1054.81万元和2779.49万元，分别占公司2022年度营业收入的0.50%和1.31%。",
            "date_modified": "2023-06-30T08:48:51.000Z"
        },
        {
            "id": 3160176,
            "content_html": "",
            "url": "https://finance.sina.cn/7x24/2023-06-30/detail-imyzafim1014010.d.html",
            "title": "【沪农商行：公司获准在全国银行间市场及境外市场发行金融债券】沪农商行公告，公司获准在全国银行间市场及境外市场发行金融债券，2023年金融债券新增余额不超过110亿元，年末金融债券余额不超过310亿元。",
            "date_modified": "2023-06-30T08:48:42.000Z"
        },
        {
            "id": 3160175,
            "content_html": "",
            "url": "https://finance.sina.cn/7x24/2023-06-30/detail-imyzafin7790922.d.html",
            "title": "汇丰银行：利率持续上升将对2024年以后的石油需求产生负面影响。",
            "date_modified": "2023-06-30T08:48:19.000Z"
        },
        {
            "id": 3160174,
            "content_html": "",
            "url": "https://finance.sina.cn/7x24/2023-06-30/detail-imyzafin7790575.d.html",
            "title": "【四川路桥：中期票据获准注册】四川路桥(600039)6月30日晚间公告，公司收到中国银行间市场交易商协会下发的接受注册通知书，交易商协会决定接受公司中期票据注册，中期票据注册金额为20亿元。",
            "date_modified": "2023-06-30T08:47:23.000Z"
        },
        {
            "id": 3160173,
            "content_html": "",
            "url": "https://finance.sina.cn/7x24/2023-06-30/detail-imyzafim1013400.d.html",
            "title": "【吉贝尔：拟定增募资不超过2.98亿元】吉贝尔公告，拟定增募资不超过2.98亿元，用于JJH201501研发项目（Ⅲ期临床研究）、高端制剂研发中心建设项目。",
            "date_modified": "2023-06-30T08:47:16.000Z"
        },
        {
            "id": 3160172,
            "content_html": "",
            "url": "https://finance.sina.cn/7x24/2023-06-30/detail-imyzafin7790161.d.html",
            "title": "【中毅达澄清：公司正在稳步推进本次重组事项】中毅达发布澄清公告，公司正在稳步推进本次重组事项，“借壳失败”属于个别股票交易软件对公司公告的错误解读。",
            "date_modified": "2023-06-30T08:46:39.000Z"
        },
        {
            "id": 3160171,
            "content_html": "",
            "title": "【广州开发区上市公司排名全国经开区第一，达80家】近日广州安凯微电子股份有限公司在上海证券交易所科创板成功上市。广州黄埔区、广州开发区上市公司累计达到80家，其中科创板上市企业10家，占全市约六成。截至目前，该区上市公司数量位居广州市各区第一、全国经开区首位。据统计，2022年该区上市公司的总营收达到3806.9亿元，毛利总计835亿元，总资产、净利润、研发强度保持增长态势，其中A股上市公司数量与福田、吴中、宝安等先进地区属同一梯队。（广州日报）",
            "date_modified": "2023-06-30T08:46:18.000Z"
        },
        {
            "id": 3160170,
            "content_html": "",
            "url": "https://finance.sina.cn/7x24/2023-06-30/detail-imyzafin7789645.d.html",
            "title": "【浙大网新：全资子公司中标杭州智慧电子政务云平台一（2023）项目】浙大网新公告，公司全资子公司华通云数据于近日中标了杭州智慧电子政务云平台一（2023）项目，项目金额最高不超过项目预算1.08亿元。",
            "date_modified": "2023-06-30T08:45:43.000Z"
        },
        {
            "id": 3160169,
            "content_html": "",
            "url": "https://finance.sina.cn/7x24/2023-06-30/detail-imyzafin7789542.d.html",
            "title": "【财信证券完成财报更新 上交所恢复其IPO审核】上交所最新披露信息显示，IPO排队的财信证券已更新提交相关财务资料，根据相关上市审核规定，6月29日，上交所恢复财信证券发行上市审核。此前，财信证券因为财报更新于发行上市申请文件中记载财务资料已过有效期，需要补充提交，根据上市相关审核规定，上交所于3月31日中止其发行上市审核。",
            "date_modified": "2023-06-30T08:45:34.000Z"
        },
        {
            "id": 3160168,
            "content_html": "",
            "url": "https://finance.sina.cn/7x24/2023-06-30/detail-imyzafin7788617.d.html",
            "title": "【外汇局：一季度我国经常账户顺差5575亿元 资本和金融账户逆差5222亿元】国家外汇管理局公布2023年一季度我国国际收支平衡表。2023年一季度，我国经常账户顺差5575亿元，资本和金融账户逆差5222亿元。按美元计值，2023年一季度，我国经常账户顺差815亿美元，其中，货物贸易顺差1299亿美元，服务贸易逆差472亿美元，初次收入逆差66亿美元，二次收入顺差54亿美元。",
            "date_modified": "2023-06-30T08:43:14.000Z"
        },
        {
            "id": 3160167,
            "content_html": "",
            "title": "【广州开发区上市公司排名全国经开区第一，达80家】据广州日报6月30日消息，近日广州安凯微电子股份有限公司在上海证券交易所科创板成功上市。广州黄埔区、广州开发区上市公司累计达到80家，其中科创板上市企业10家，占全市约六成。截至目前，该区上市公司数量位居广州市各区第一、全国经开区首位。据统计，2022年该区上市公司的总营收达到3806.9亿元，毛利总计835亿元，总资产、净利润、研发强度保持增长态势，其中A股上市公司数量与福田、吴中、宝安等先进地区属同一梯队。",
            "date_modified": "2023-06-30T08:42:18.000Z"
        },
        {
            "id": 3160166,
            "content_html": "",
            "url": "https://finance.sina.cn/7x24/2023-06-30/detail-imyzafim1010877.d.html",
            "title": "【国家外汇管理局公布2023年5月我国国际收支货物和服务贸易数据】2023年5月，我国国际收支货物和服务贸易进出口规模38112亿元，同比增长1%。其中，货物贸易出口18400亿元，进口14792亿元，顺差3608亿元；服务贸易出口1792亿元，进口3128亿元，逆差1336亿元。服务贸易主要项目为：运输服务进出口规模1583亿元，旅行服务进出口规模1082亿元，其他商业服务进出口规模880亿元，电信、计算机和信息服务进出口规模581亿元。",
            "date_modified": "2023-06-30T08:41:42.000Z"
        },
        {
            "id": 3160165,
            "content_html": "",
            "url": "https://finance.sina.cn/7x24/2023-06-30/detail-imyzafim1010612.d.html",
            "title": "【中毅达：“借壳失败”属于个别股票交易软件对公司公告的错误解读】中毅达发布澄清公告，公司正在稳步推进本次重组事项，“借壳失败”属于个别股票交易软件对公司公告的错误解读。",
            "date_modified": "2023-06-30T08:41:06.000Z"
        },
        {
            "id": 3160164,
            "content_html": "",
            "url": "https://finance.sina.cn/7x24/2023-06-30/detail-imyzafin7787471.d.html",
            "title": "【华丽家族：拟于7月17日召开2023年第一次临时股东大会，审议分红预案等事项】公司拟于2023年7月17日在上海市松江区石湖荡镇三新公路207号会议室召开2023年第一次临时股东大会。会议审议事项包括关于2022年度利润分配预案的议案、关于续聘2023年度财务和内控审计机构的议案、关于2023年度担保计划的议案、关于公司子公司为购房客户金融机构按揭贷款提供阶段性担保的议案、关于公司及下属子公司进行融资并授权公司管理层办理融资相关事项的议案。",
            "date_modified": "2023-06-30T08:40:13.000Z"
        }
    ]
}