{
    "version": "https://jsonfeed.org/version/1",
    "title": "sina news",
    "home_page_url": "https://abuqi.github.io/sina-news",
    "feed_url": "https://abuqi.github.io/sina-news/rss.json",
    "description": "sina news zhibo",
    "items": [
        {
            "id": 3232328,
            "content_html": "",
            "url": "https://finance.sina.cn/7x24/2023-09-06/detail-imzktuni7396203.d.html",
            "title": "【福州持续强降雨突破历史极值 147个乡镇超5万人受灾 经济损失约5亿元】9月6日，据央视新闻消息，受台风“海葵”影响，福州持续性强降雨突破历史极值。5日21时至6日5时925个乡镇降雨量超250毫米，最大为盖山镇439.7毫米。截至6日8时，受灾乡镇147个，受灾人员51272人，紧急转移人口36026人；城区严重受淹小区63个，小区车库进水44个，受淹城中村16个；受淹农田4194公顷，受损公路桥梁170处，倒塌房屋67间，已造成直接经济损失约5.521亿元。",
            "date_modified": "2023-09-06T02:18:01.000Z"
        },
        {
            "id": 3232327,
            "content_html": "",
            "url": "https://finance.sina.cn/7x24/2023-09-06/detail-imzktuni7395945.d.html",
            "title": "【加拿大安大略教师养老基金将收购英国理财公司7IM多数股权】加拿大安大略省教师养老金计划（OTPP）9月5日发布声明，宣布已达成最终协议，将从Caledonia Investments手中收购英国财富管理公司7IM的多数股权。7IM成立于2002年，管理着约210亿美元资产。（界面新闻）",
            "date_modified": "2023-09-06T02:16:58.000Z"
        },
        {
            "id": 3232326,
            "content_html": "",
            "title": "【日本黄金零售价格再创新高】据央视新闻，当地时间9月6日，被视作日本黄金零售指标价格的田中贵金属工业黄金柜台销售价格达到每克10105日元（约合人民币499元），再创历史新高。",
            "date_modified": "2023-09-06T02:16:38.000Z"
        },
        {
            "id": 3232325,
            "content_html": "",
            "url": "https://finance.sina.cn/7x24/2023-09-06/detail-imzktunh0618677.d.html",
            "title": "【巴西8月新能源车销量增长迅速】据央视新闻，当地时间9月5日，巴西全国汽车制造商协会（Anfavea）发布该国汽车销售最新数据。数据显示，巴西新车（乘用车、轻型商用车、卡车和公交车）销量在8月总体保持稳定，共售出20.77万辆，较去年同期下降0.4%，而较今年7月下降7.9%。业内人士分析认为，此前巴西政府推出购车享受折扣的临时措施，一度推动了汽车销量的上涨。",
            "date_modified": "2023-09-06T02:16:22.000Z"
        },
        {
            "id": 3232324,
            "content_html": "",
            "url": "https://finance.sina.cn/7x24/2023-09-06/detail-imzktunh0618539.d.html",
            "title": "【刘家峡水库今天起加大出库流量 支持抗旱减灾】 据央视新闻，记者从相关部门了解到，刘家峡水电厂今天起将水库出库流量加大到1400立方米每秒，日出库水量由6050万立方米增加至1.21亿立方米，为流域抗旱减灾提供水资源保障。",
            "date_modified": "2023-09-06T02:15:59.000Z"
        },
        {
            "id": 3232323,
            "content_html": "",
            "url": "https://finance.sina.cn/7x24/2023-09-06/detail-imzktuni7395635.d.html",
            "title": "【卫星导航概念持续走强 神宇股份涨停】 卫星导航概念持续走强，截至发稿，神宇股份涨停，华力创通涨超17%，利扬芯片、硕贝德、天银机电、航宇微、天箭科技等涨幅居前。",
            "date_modified": "2023-09-06T02:15:55.000Z"
        },
        {
            "id": 3232322,
            "content_html": "",
            "title": "丰田汽车：上个月的故障发生在维护工作期间。故障由服务器问题引起。确认系统问题不是由网络攻击引起的。",
            "date_modified": "2023-09-06T02:15:40.000Z"
        },
        {
            "id": 3232321,
            "content_html": "",
            "url": "https://finance.sina.cn/7x24/2023-09-06/detail-imzktuni7394605.d.html",
            "title": "【中国民营火箭首次海上发射成功】 9月5日17点34分，在太原卫星发射中心海上发射团队支持下，来自北京的民营火箭公司星河动力航天于黄海海域圆满完成谷神星一号海射型（遥一）运载火箭发射任务，顺利将天启星座21星至24星送入800公里预定轨道。这是中国民营火箭公司首次开展海上发射任务并取得成功。 (北京日报)",
            "date_modified": "2023-09-06T02:13:24.000Z"
        },
        {
            "id": 3232320,
            "content_html": "",
            "url": "https://finance.sina.cn/7x24/2023-09-06/detail-imzktqek0747616.d.html",
            "title": "【福建东部和南部今天还有暴雨或大暴雨】据中央气象台，福建东部和南部今天还有暴雨或大暴雨，大家还是不能掉以轻心。明天，福建的雨会明显减弱。 此外，未来三天，广东、广西东部、江西南部、湖南南部等地也会有大到暴雨，局地大暴雨。",
            "date_modified": "2023-09-06T02:11:57.000Z"
        },
        {
            "id": 3232319,
            "content_html": "",
            "url": "https://finance.sina.cn/7x24/2023-09-06/detail-imzktqen9446934.d.html",
            "title": "【今年暑假港人“北上”超900万人次 大湾区深度融合再提速】今年暑假，探亲流、旅游流、商务流激增，港人“北上”的热度急升，一度超过了“南下”的内地旅客人数。香港入境事务处统计数据显示，7月1日至8月29日，已有超过900万人次港人入境深圳，而香港总人口数为733.32万人。这意味着，今年暑假期间，平均每位香港人入境深圳1.2次。“南下”到港的内地旅客及其他旅客为533万人次。从今年1月内地与香港恢复通关到“港车北上”政策落地实施，内地游客蜂拥挤满“购物天堂”香港的同时，港人“北上”消费的热度也持续高涨。跨境流动呈现“双向奔赴”趋势。人流趋势的背后折射出粤港澳三地消费圈、生活圈、文化圈、商务圈深度融合再提速。",
            "date_modified": "2023-09-06T02:11:42.000Z"
        },
        {
            "id": 3232318,
            "content_html": "",
            "title": "【保障经济困难学生入学 本年度高校学生助学贷款申请已达581万人】教育部全国资助管理中心有关负责人介绍，2023年度高校学生助学贷款受理起止时间为7月15日至9月30日，截止到目前，全国申请助学贷款学生已达581万人，贷款金额594亿元，较2022年全年发放金额571.14亿元增长4%。",
            "date_modified": "2023-09-06T02:10:17.000Z"
        },
        {
            "id": 3232317,
            "content_html": "",
            "url": "https://finance.sina.cn/7x24/2023-09-06/detail-imzktqek0746434.d.html",
            "title": "【波音与飞机租赁公司Aviation Capital敲定13架737 MAX订单】9月5日，波音与飞机租赁公司Aviation Capital Group在声明中表示，双方敲定13架737 MAX喷气式飞机订单，其中包括7架737-8和6架737-10喷气式飞机，使得后者的737 MAX订单规模增至47架。",
            "date_modified": "2023-09-06T02:08:41.000Z"
        },
        {
            "id": 3232316,
            "content_html": "",
            "url": "https://finance.sina.cn/7x24/2023-09-06/detail-imzktqem7523227.d.html",
            "title": "【浙江重新公布征地补偿最低保护标准】浙江省自然资源厅近日印发《关于重新公布全省征地区片综合地价最低保护标准的通知》，自发文之日起施行，有效期3年。征地区片综合地价由土地补偿费和安置补助费两部分组成。全省征收农民集体所有农用地区片综合地价最低保护标准：征收农用地（不含林地），一类地区不低于6.2万元/亩、二类地区不低于5.6万元/亩、三类地区不低于4.8万元/亩。征收农民集体所有建设用地，按征收农用地区片综合地价标准执行；征收林地和农民集体所有未利用地，按不低于征收农用地区片综合地价标准的60%执行。",
            "date_modified": "2023-09-06T02:07:58.000Z"
        },
        {
            "id": 3232315,
            "content_html": "",
            "url": "https://finance.sina.cn/7x24/2023-09-06/detail-imzktqef7659535.d.html",
            "title": "【港口航运板块震荡走低 中远海能逼近跌停】 港口航运板块震荡走低，中远海能逼近跌停，招商轮船、招商南油、海通发展、中远海特等跟跌。",
            "date_modified": "2023-09-06T02:07:39.000Z"
        },
        {
            "id": 3232314,
            "content_html": "",
            "title": "A股军工板块异动拉升，晨曦航空大涨9%，恒宇信通、新余国科、航宇科技、安达维尔、航亚科技等纷纷冲高。",
            "date_modified": "2023-09-06T02:06:40.000Z"
        },
        {
            "id": 3232313,
            "content_html": "",
            "url": "https://finance.sina.cn/7x24/2023-09-06/detail-imzktqef7658757.d.html",
            "title": "【华虹公司：公司在手订单充足并保持稳定增长，四条生产线均保持满载运营】 华虹公司在互动平台表示，公司在手订单充足并保持稳定增长，且现阶段公司四条生产线均保持满载运营，同时受行业下游产品需求快速增长、产能持续提升等因素，公司将努力保持业务量呈逐年增加的势态。",
            "date_modified": "2023-09-06T02:05:01.000Z"
        },
        {
            "id": 3232312,
            "content_html": "",
            "url": "https://finance.sina.cn/7x24/2023-09-06/detail-imzktqek0744730.d.html",
            "title": "日本内阁官房长官松野博一：正急切关注国际能源价格。呼吁石油生产国采取措施稳定市场。",
            "date_modified": "2023-09-06T02:04:32.000Z"
        },
        {
            "id": 3232311,
            "content_html": "",
            "url": "https://finance.sina.cn/7x24/2023-09-06/detail-imzktqek0744363.d.html",
            "title": "【石油板块探底回升 准油股份3天2板】准油股份冲击涨停，中曼石油、贝肯能源、通源石油、新潮能源等纷纷冲高。消息面上，沙特宣布将减产100万桶/日的措施延长3个月至年底；俄罗斯亦宣布将延长30万桶/日的石油出口削减至12月份；布油顺势突破90美元关口，为去年11月以来首次。",
            "date_modified": "2023-09-06T02:03:22.000Z"
        },
        {
            "id": 3232310,
            "content_html": "",
            "url": "https://finance.sina.cn/7x24/2023-09-06/detail-imzktqek0744140.d.html",
            "title": "【山东民企万达股份被强执7903万】天眼查App显示，近日，万达集团股份有限公司新增一则被执行人信息，执行标的7903万余元，执行法院为东营市中级人民法院，关联案件为金融借款合同纠纷。该公司成立于1994年6月，法定代表人为尚建立，注册资本约2.95亿人民币，由万达控股集团有限公司等共同持股。",
            "date_modified": "2023-09-06T02:02:50.000Z"
        },
        {
            "id": 3232309,
            "content_html": "",
            "title": "A股无人驾驶板块异动拉升，天迈科技20CM涨停，华力创通涨13%，亚通精工此前涨停，腾景科技、光庭信息、天银机电拉升。",
            "date_modified": "2023-09-06T02:00:43.000Z"
        },
        {
            "id": 3232308,
            "content_html": "",
            "url": "https://finance.sina.cn/7x24/2023-09-06/detail-imzktqek0742754.d.html",
            "title": "【卫星导航概念股震荡走强 天迈科技20CM涨停】天迈科技20CM涨停，华力创通涨超10%，华体科技涨停，硕贝德、利扬芯片、神宇股份涨超5%。",
            "date_modified": "2023-09-06T01:59:33.000Z"
        },
        {
            "id": 3232307,
            "content_html": "",
            "url": "https://finance.sina.cn/7x24/2023-09-06/detail-imzktqen9442750.d.html",
            "title": "【美超额储蓄或将耗尽 消费景气度将明显减弱】 本轮美国经济周期的一大“动力引擎”——超额储蓄或将耗尽。据旧金山联储日前测算，截至今年6月末，美国家庭持有的超额储蓄已不足1900亿美元。该联储银行经济研究部的分析师在博客文章中写道，尽管前景存在相当大的不确定性，“但预计这些超额储蓄可能在2023年第三季度耗尽”。分析人士认为，随着美国超额储蓄从高点回落，消费景气度也将明显减弱，对美国经济的贡献作用将趋于下行。与此同时，超额储蓄逐步消耗，也可能推动部分群体回归劳动力市场，对通胀产生一定的影响。（中国证券报）",
            "date_modified": "2023-09-06T01:57:54.000Z"
        },
        {
            "id": 3232306,
            "content_html": "",
            "url": "https://finance.sina.cn/7x24/2023-09-06/detail-imzktqek0742136.d.html",
            "title": "【北向资金净卖出超10亿元】以买卖成交额口径（挂单已成交）统计，截至目前北向资金净卖出超10亿元，其中沪股通净卖出7.62亿元，深股通净卖出2.44亿元。以余额规模口径（已挂单）统计，北向资金净流出超5亿元，其中沪股通净流出5.32亿元，深股通净流出0.22亿元。",
            "date_modified": "2023-09-06T01:57:44.000Z"
        },
        {
            "id": 3232305,
            "content_html": "",
            "url": "https://finance.sina.cn/7x24/2023-09-06/detail-imzktqek0741922.d.html",
            "title": "【沪深两市成交额突破2000亿元】截至目前，沪深两市成交额突破2000亿元，其中，沪市成交额797亿元，深市成交额1203亿元。",
            "date_modified": "2023-09-06T01:57:18.000Z"
        },
        {
            "id": 3232303,
            "content_html": "",
            "url": "https://finance.sina.cn/7x24/2023-09-06/detail-imzktqek0741472.d.html",
            "title": "【前天合光能副总裁离职创业干储能，红杉鼎晖都投了】前天合光能副总裁、海外系统事业部总裁尤泓明已离职并创立了新公司——揽海能源（长兴）有限公司（以下简称“揽海能源”），聚焦于海外储能业务。揽海能源成立于2023年1月，今年6月宣布完成了超亿元融资，此时距离其成立还不到5个月。该轮融资由红杉中国领投，鼎晖VGC（创新与成长基金）跟投。募得资金主要用于全面展开全球中大型储能资产创设、储能产品和系统的技术研发、产品迭代以及运营推广。（36氪）",
            "date_modified": "2023-09-06T01:55:53.000Z"
        },
        {
            "id": 3232302,
            "content_html": "",
            "url": "https://finance.sina.cn/7x24/2023-09-06/detail-imzktqek0741129.d.html",
            "title": "港股持续走低，恒生科技指数跌幅扩大至1.6%，恒指跌0.9%。",
            "date_modified": "2023-09-06T01:54:44.000Z"
        },
        {
            "id": 3232301,
            "content_html": "",
            "title": "据贵州省纪委监委消息：贵州省自然资源厅党委委员、副厅长吴月平涉嫌严重违纪违法，目前正接受贵州省纪委监委纪律审查和监察调查。",
            "date_modified": "2023-09-06T01:53:33.000Z"
        },
        {
            "id": 3232300,
            "content_html": "",
            "url": "https://finance.sina.cn/7x24/2023-09-06/detail-imzktqem7517775.d.html",
            "title": "【光刻机板块持续走高 张江高科等多股涨停】光刻机、光刻胶板块持续走高，张江高科、扬帆新材、盛剑环境、蓝英装备等多股涨停，容大感光、怡达股份、飞凯材料、高盟新材等多股涨超5%。",
            "date_modified": "2023-09-06T01:53:08.000Z"
        },
        {
            "id": 3232299,
            "content_html": "",
            "url": "https://finance.sina.cn/7x24/2023-09-06/detail-imzktqem7517689.d.html",
            "title": "【上海房地产交易中心调研“认房不认贷”落地效果，了解挂牌量、房价波动等】上海市房地产交易中心相关部门于9月4日组织头部中介机构召开讨论会，会议主要沟通近期房地产市场的有关情况并了解“认房不认贷”新政实施效果，包括新增客户、挂牌量、转定情况、房价波动等内容。另据了解，相关平台机构条线负责人亦汇报了相关情况。据悉，上海市统计局相关部门还将于近期召集经纪机构进一步讨论相关问题。（澎湃新闻）",
            "date_modified": "2023-09-06T01:52:48.000Z"
        },
        {
            "id": 3232298,
            "content_html": "",
            "url": "https://finance.sina.cn/7x24/2023-09-06/detail-imzktqen9441574.d.html",
            "title": "【和远气体：2023年和2024年公司有望实现良好增长态势】 和远气体9月5日接待机构调研时展望未来业绩称，随着公司两大电子特气和电子化学品产业园及其他工业气体项目的建成投产，未来将形成电子特气及电子化学品、硅基功能性新材料及大宗工业气体三大版块的齐头并进，2023年和2024年公司有望实现良好的增长态势，公司有信心实现2025年产值达到50亿元的目标。",
            "date_modified": "2023-09-06T01:52:35.000Z"
        },
        {
            "id": 3232297,
            "content_html": "",
            "url": "https://finance.sina.cn/7x24/2023-09-06/detail-imzktqem7516842.d.html",
            "title": "【辽宁朝阳：支持提取公积金支付首付款，放宽多子女家庭贷款额度限制】 据澎湃，9月5日，辽宁省朝阳市发布住房公积金管理实施5项惠民政策，自2023年9月1日起。政策一：朝阳市将支持提取住房公积金支付购房首付款；政策二：提高住房公积金租房提取额度，由原来的900元/月提高至1000元/月；政策三：优化住房公积金租房提取频次。为满足缴存职工支付房租的实际需求，将原租房提取频次由1次/年，调整为可以1次/月；政策四：多子女家庭租房提取不设最高提取限额；政策五：放宽高层次人才、多子女家庭贷款额度限制。",
            "date_modified": "2023-09-06T01:50:27.000Z"
        },
        {
            "id": 3232296,
            "content_html": "",
            "url": "https://finance.sina.cn/7x24/2023-09-06/detail-imzktqem7516575.d.html",
            "title": "【华创证券：期待白酒中秋国庆旺季表现，优选确定性龙头】华创证券9月6日研报指出，期待白酒板块中秋国庆旺季表现，优选确定性龙头。当前旺季双节回款陆续启动，酒企促回款、拉动销动作密集，旺季有望实现小幅量增、价格企稳、挤压增长。首选业绩确定性与景气度兼具的茅台（业绩确定性极强，经营治理全面改善），汾酒（营销体系已回正轨，业绩及基本面依然强势），老窖（管理层和团队最市场化，业绩弹性仍足）；其次推荐五粮液、洋河，均具备较强的基本面和较高性价比的估值，建议加大关注。持续推荐今世缘、古井等区域龙头，经营稳健业绩确定性强。",
            "date_modified": "2023-09-06T01:49:45.000Z"
        },
        {
            "id": 3232295,
            "content_html": "",
            "url": "https://finance.sina.cn/7x24/2023-09-06/detail-imzktqem7516479.d.html",
            "title": "【上海电气被纳入恒生可持续发展三大指数】 近日，从恒生指数有限公司获悉，上海电气同时被纳入恒生可持续发展系列指数，即恒生A股可持续发展企业指数、恒生内地及香港可持续发展企业指数、恒生A股可持续发展企业基准指数，该调整于2023年9月4日起生效。",
            "date_modified": "2023-09-06T01:49:23.000Z"
        },
        {
            "id": 3232294,
            "content_html": "",
            "url": "https://finance.sina.cn/7x24/2023-09-06/detail-imzktqem7516201.d.html",
            "title": "【数据要素概念股盘初走低】 数据要素概念股盘初走低，浩瀚深度、先进数通、汇纳科技跌超6%，天阳科技、君逸数码、山大地纬、海量数据、久远银海等跟跌。",
            "date_modified": "2023-09-06T01:48:45.000Z"
        },
        {
            "id": 3232293,
            "content_html": "",
            "url": "https://finance.sina.cn/7x24/2023-09-06/detail-imzktqem7516036.d.html",
            "title": "【韩国索路思高新材料子公司将斥资近5.5亿美元，在加拿大建电动汽车电池用铜箔工厂】9月5日，韩国索路思高新材料子公司Volta Energy Solutions宣布将在加拿大魁北克省格兰比投资7.5亿加元（约合5.5亿美元），建设电动汽车电池用铜箔工厂，计划2026年实现量产，目标年产能为2.5万吨。魁北克省将为上述项目提供1.5亿加元贷款。如果Volta Energy Solutions满足在工厂保留260个工作岗位等条件，则部分贷款将被免除。（界面新闻）",
            "date_modified": "2023-09-06T01:48:20.000Z"
        },
        {
            "id": 3232292,
            "content_html": "",
            "title": "港股汽车股走低，小鹏汽车(09868.HK)跌4%，理想汽车(02015.HK)跌近3%，零跑汽车(09863.HK)、蔚来汽车(09866.HK)跌超2%。",
            "date_modified": "2023-09-06T01:47:15.000Z"
        },
        {
            "id": 3232291,
            "content_html": "",
            "url": "https://finance.sina.cn/7x24/2023-09-06/detail-imzktqem7515600.d.html",
            "title": "【游戏、传媒股盘初下挫】 游戏、传媒股盘初下挫，宝通科技跌超5%，恺英网络、金逸影视、冰川网络、神州泰岳、巨人网络等多股跌超3%。",
            "date_modified": "2023-09-06T01:47:09.000Z"
        },
        {
            "id": 3232290,
            "content_html": "",
            "url": "https://finance.sina.cn/7x24/2023-09-06/detail-imzktqem7515562.d.html",
            "title": "【受持续暴雨影响 福州机场专线临时停运】 据央视新闻，今天，福州全市有大雨到暴雨，部分乡镇有大暴雨（最大可能出现在福清、长乐中南部、永泰东部、闽侯中南部、罗源东北部和高新区）。24小时雨量80-150毫米，局部超过200毫米。受持续暴雨影响，福州及周边地市至长乐机场路面多处积水，道路通行受阻，为确保广大乘客的出行安全，福州机场专线临时停运，具体恢复时间将结合道路通行情况另行通知。",
            "date_modified": "2023-09-06T01:47:02.000Z"
        },
        {
            "id": 3232289,
            "content_html": "",
            "url": "https://finance.sina.cn/7x24/2023-09-06/detail-imzktqek0737601.d.html",
            "title": "我乐家居盘中触及涨停，录得8连板。",
            "date_modified": "2023-09-06T01:45:01.000Z"
        },
        {
            "id": 3232288,
            "content_html": "",
            "url": "https://finance.sina.cn/7x24/2023-09-06/detail-imzktqen9439415.d.html",
            "title": "【宝能集团因拖欠工资被罚5万】天眼查App显示，近日，深圳市宝能投资集团有限公司因未依法及时足额支付305名员工2022年3月-2023年4月工资，被深圳市罗湖区人力资源局罚款5万元。值得一提的是，去年5月，该公司已因未依法及时足额支付414名员工工资且经劳动保障部门责令改正逾期未改正，被罚款5万元。此外，风险信息显示，该公司已多次因劳动争议纠纷被法院强制执行、限制高消费、列为失信被执行人（老赖）。",
            "date_modified": "2023-09-06T01:44:52.000Z"
        },
        {
            "id": 3232287,
            "content_html": "",
            "title": "BC电池板块持续拉涨，广信材料20CM涨停，实现两连板，帝尔激光涨12%，爱旭股份、英诺激光、罗博特科、隆基绿能跟涨。",
            "date_modified": "2023-09-06T01:43:41.000Z"
        },
        {
            "id": 3232286,
            "content_html": "",
            "url": "https://finance.sina.cn/7x24/2023-09-06/detail-imzktqem7514324.d.html",
            "title": "【碧桂园涨近5% 昨日已完成支付两笔境外债票息】截至发稿，碧桂园(02007.HK)涨4.95%。消息方面，碧桂园在9月5日完成了两笔合计2250万美元的境外债票息的支付，继续保持仍未实质性违约的状态。业内人士表示，随着市场企稳回升，部分企业债务重组出现重大进展，销售数据明显回暖，港股内资地产股或迎来估值重构。",
            "date_modified": "2023-09-06T01:43:36.000Z"
        },
        {
            "id": 3232285,
            "content_html": "",
            "url": "https://finance.sina.cn/7x24/2023-09-06/detail-imzktqem7514280.d.html",
            "title": "【国盛证券：短期鸡价深跌或带动淘汰增多，利好后期价格反转幅度】国盛证券9月6日研报指出，由于毛鸡行情疲软，补栏热情再度回落，淘汰种鸡趋势有所上升，据Mysteel农产品市场调研，当前市场淘汰种鸡有增量现象，淘鸡周龄处于55周以上，短期鸡价深跌或带动淘汰增多，利好后期价格反转幅度。本年度在父母代存栏上行的基础上鸡苗价格中枢明显上移，反映下游需求上升或存栏种鸡性能下降，往后看2022年低祖代更新量链条式反应仍在发生，预计年底价格至明年上半年鸡价或迎来反转。",
            "date_modified": "2023-09-06T01:43:32.000Z"
        },
        {
            "id": 3232284,
            "content_html": "",
            "url": "https://finance.sina.cn/7x24/2023-09-06/detail-imzktqef7652699.d.html",
            "title": "【21个行业获融资净买入，银行行业获净买入最多】据Wind统计显示，申万所属的31个一级行业，9月5日共有21个行业板块获融资净买入，净买入金额在1亿元以上的有8个。其中，银行行业获融资净买入额居首，当日净买入5.51亿元；融资净买入的还有电子、非银金融、电力设备、房地产、建筑装饰、国防军工等行业。",
            "date_modified": "2023-09-06T01:42:09.000Z"
        },
        {
            "id": 3232283,
            "content_html": "",
            "title": "日本央行审议委员高田创：日本可能正处于价格标准变化的转折点。挑战在于实现工资的良性循环。",
            "date_modified": "2023-09-06T01:41:17.000Z"
        },
        {
            "id": 3232282,
            "content_html": "",
            "url": "https://finance.sina.cn/7x24/2023-09-06/detail-imzktqem7513443.d.html",
            "title": "【出口拉动经济增长 澳大利亚经济经受住了加息考验】在商品和服务出口需求强劲的推动下，澳大利亚经济在截至6月份的三个月里保持了增长势头，这表明面对12次加息，澳大利亚经济仍有强劲的动力。这一结果将增强澳洲联储的信心，即它可以在冷却通胀的同时，使经济实现软着陆。尽管整体数据强劲，但澳大利亚的经济扩张可能会从现在开始减弱。首先，亚洲地区经济前景的不确定性越来越大；其次，澳大利亚家庭已经面临资金紧张，周三公布的数据显示，他们的储蓄率已降至从三个月前向下修正的3.6%降至3.2%。",
            "date_modified": "2023-09-06T01:41:04.000Z"
        },
        {
            "id": 3232281,
            "content_html": "",
            "url": "https://finance.sina.cn/7x24/2023-09-06/detail-imzktqem7513106.d.html",
            "title": "【智能驾驶板块异动拉升 亚通精工涨停】亚通精工涨停，天迈科技大涨超10%，兴民智通、豪恩汽电、赛力斯、浙江世宝等跟涨。消息面上，武汉召开的智能网联汽车创新与应用发展论坛上，百度集团资深副总裁李震宇表示，到2025年，在中国的某个城市，将实现L4级别无人驾驶规模化运营。",
            "date_modified": "2023-09-06T01:40:13.000Z"
        },
        {
            "id": 3232280,
            "content_html": "",
            "url": "https://finance.sina.cn/7x24/2023-09-06/detail-imzktqek0735930.d.html",
            "title": "【三一重能于河北新设风电装备子公司】 企查查APP显示，近日，三一（邢台）风电装备有限公司成立，注册资本1000万元，经营范围包含：发电机及发电机组制造；风电场相关系统研发；新能源原动设备制造；新能源原动设备销售等。企查查股权穿透显示，该公司由三一重能100%控股。",
            "date_modified": "2023-09-06T01:40:01.000Z"
        },
        {
            "id": 3232279,
            "content_html": "",
            "url": "https://finance.sina.cn/7x24/2023-09-06/detail-imzktqem7512851.d.html",
            "title": "【研究发现3D打印黑磷支架能够促进骨缺损修复】 据科技日报，从中国科学院深圳先进技术研究院获悉，该院研究员赖毓霄团队采用低温沉积3D打印技术，研发了一种可降解高分子复合黑磷的多功能仿生多孔支架，首次探讨了黑磷支架在植入骨组织中引起的免疫响应功能。该支架能够通过调控免疫系统影响免疫微环境，从而有效促进骨缺损修复，具有广阔的临床应用前景。相关研究成果近日发表在《先进科学》上。",
            "date_modified": "2023-09-06T01:39:29.000Z"
        },
        {
            "id": 3232278,
            "content_html": "",
            "url": "https://finance.sina.cn/7x24/2023-09-06/detail-imzktqek0735712.d.html",
            "title": "【沪深两市成交额突破1000亿元】截至目前，沪深两市成交额突破1000亿元，其中，沪市成交额390亿元，深市成交额609亿元。",
            "date_modified": "2023-09-06T01:39:23.000Z"
        }
    ]
}